flight_tracker_mcp/__init__.py
flight_tracker_mcp/__main__.py
flight_tracker_mcp-0.1.0.dist-info/licenses/LICENSE
flight_tracker_mcp-0.1.0.dist-info/METADATA
flight_tracker_mcp-0.1.0.dist-info/WHEEL
flight_tracker_mcp-0.1.0.dist-info/entry_points.txt
flight_tracker_mcp-0.1.0.dist-info/top_level.txt
flight_tracker_mcp-0.1.0.dist-info/RECORD
