Metadata-Version: 2.4
Name: flight-tracker-mcp
Version: 0.1.0
Summary: MCP Server for flight tracking using OpenSky Network API
Home-page: https://github.com/GenAICPA/flight_tracker
Author: Eric
Author-email: your-email@example.com
License: MIT
Project-URL: Repository, https://github.com/GenAICPA/flight_tracker
Project-URL: Issues, https://github.com/GenAICPA/flight_tracker/issues
Keywords: mcp,flight,tracking,aviation,opensky
Classifier: Development Status :: 3 - Alpha
Classifier: Intended Audience :: Developers
Classifier: License :: OSI Approved :: MIT License
Classifier: Programming Language :: Python :: 3
Classifier: Programming Language :: Python :: 3.8
Classifier: Programming Language :: Python :: 3.9
Classifier: Programming Language :: Python :: 3.10
Classifier: Programming Language :: Python :: 3.11
Classifier: Programming Language :: Python :: 3.12
Requires-Python: >=3.8
License-File: LICENSE
Requires-Dist: mcp[cli]>=1.11.0
Requires-Dist: opensky-api>=1.3.0
Requires-Dist: aiohttp>=3.8.0
Requires-Dist: requests>=2.28.0
Dynamic: author
Dynamic: author-email
Dynamic: classifier
Dynamic: description
Dynamic: description-content-type
Dynamic: home-page
Dynamic: keywords
Dynamic: license
Dynamic: license-file
Dynamic: project-url
Dynamic: requires-dist
Dynamic: requires-python
Dynamic: summary
